btpy/__init__.py
btpy/__main__.py
btpy/device/__init__.py
btpy/device/beacon.py
btpy/device/classic.py
btpy/device/le.py
btpy-2.0.9.dist-info/METADATA
btpy-2.0.9.dist-info/WHEEL
btpy-2.0.9.dist-info/entry_points.txt
btpy-2.0.9.dist-info/licenses/LICENSE
btpy-2.0.9.dist-info/RECORD
