Metadata-Version: 2.4
Name: btpy
Version: 2.0.9
Project-URL: Homepage, https://github.com/nbdy/btpy
Project-URL: Documentation, https://github.com/nbdy/btpy/wiki
Project-URL: Repository, https://github.com/nbdy/btpy.git
Project-URL: Issues, https://github.com/nbdy/btpy/issues
Project-URL: Changelog, https://github.com/nbdy/btpy/blob/main/CHANGELOG.md
Author: nbdy
Maintainer: nbdy
License: MIT License
License-File: LICENSE
Keywords: beacon,ble,bluetooth,classic,library
Classifier: Development Status :: 4 - Beta
Classifier: License :: OSI Approved :: MIT License
Classifier: Programming Language :: Python :: 3.10
Classifier: Programming Language :: Python :: 3.11
Classifier: Programming Language :: Python :: 3.12
Requires-Python: >=3.10
Requires-Dist: beacontools[scan]==2.1.0
Requires-Dist: bleak==1.1.1
Requires-Dist: bumble>=0.0.210
